pysertive/__init__.py
pysertive/core.py
pysertive-0.0.1.dist-info/LICENSE.txt
pysertive-0.0.1.dist-info/METADATA
pysertive-0.0.1.dist-info/WHEEL
pysertive-0.0.1.dist-info/RECORD
