Metadata-Version: 2.1
Name: pysertive
Version: 0.0.1
Summary: 
Home-page: https://github.com/abeltavares/pysertive
Keywords: python,contract-programming,design-by-contract,preconditions,postconditions,invariants,code-quality,code-verification,software-reliability
Author: Abel Tavares
Author-email: abelst9@gmail.com
Requires-Python: >=3.10,<4.0
Classifier: Development Status :: 5 - Production/Stable
Classifier: Environment :: Console
Classifier: Intended Audience :: Developers
Classifier: License :: OSI Approved :: MIT License
Classifier: Operating System :: OS Independent
Classifier: Programming Language :: Python
Classifier: Programming Language :: Python :: 3
Classifier: Programming Language :: Python :: 3.10
Classifier: Programming Language :: Python :: 3.11
Classifier: Programming Language :: Python :: 3.12
Classifier: Programming Language :: Python :: 3 :: Only
Classifier: Programming Language :: Python :: Implementation :: CPython
Classifier: Topic :: Software Development :: Libraries :: Python Modules
Classifier: Topic :: Software Development :: Quality Assurance
Classifier: Topic :: Software Development :: Testing
Classifier: Typing :: Typed
Project-URL: Repository, https://github.com/abeltavares/pysertive.git
